[
  {
    "id": 8,
    "active": true,
    "date": "2025-01-22T17:59:11.824Z",
    "totalPrice": 4500
  },
  {
    "id": 9,
    "active": true,
    "date": "2025-01-22T18:09:39.580Z",
    "totalPrice": 1500
  },
  {
    "id": 10,
    "active": true,
    "date": "2025-01-22T18:13:17.054Z",
    "totalPrice": 2500
  },
  {
    "id": 11,
    "active": true,
    "date": "2025-01-22T18:58:54.747Z",
    "totalPrice": 3900
  },
  {
    "id": 12,
    "active": true,
    "date": "2025-01-22T19:09:06.856Z",
    "totalPrice": 3000
  },
  {
    "id": 13,
    "active": true,
    "date": "2025-01-22T19:10:29.225Z",
    "totalPrice": 4000
  },
  {
    "id": 14,
    "active": true,
    "date": "2025-01-22T19:27:43.589Z",
    "totalPrice": 2000
  },
  {
    "id": 15,
    "active": true,
    "date": "2025-01-22T19:48:36.172Z",
    "totalPrice": 5745
  },
  {
    "id": 16,
    "active": true,
    "date": "2025-01-22T19:54:42.678Z",
    "totalPrice": 2000
  },
  {
    "id": 17,
    "active": true,
    "date": "2025-01-22T20:24:23.318Z",
    "totalPrice": 2800
  },
  {
    "id": 18,
    "active": true,
    "date": "2025-01-22T21:38:32.277Z",
    "totalPrice": 5790
  },
  {
    "id": 19,
    "active": true,
    "date": "2025-01-22T21:38:55.296Z",
    "totalPrice": 2500
  },
  {
    "id": 20,
    "active": true,
    "date": "2025-01-23T10:51:15.544Z",
    "totalPrice": 2500
  },
  {
    "id": 21,
    "active": true,
    "date": "2025-01-23T11:07:11.019Z",
    "totalPrice": 300
  },
  {
    "id": 22,
    "active": true,
    "date": "2025-01-23T11:16:54.174Z",
    "totalPrice": 2000
  },
  {
    "id": 23,
    "active": true,
    "date": "2025-01-23T11:44:52.004Z",
    "totalPrice": 600
  },
  {
    "id": 25,
    "active": true,
    "date": "2025-01-23T12:11:12.212Z",
    "totalPrice": 6400
  },
  {
    "id": 26,
    "active": true,
    "date": "2025-01-23T17:12:16.238Z",
    "totalPrice": 3300
  },
  {
    "id": 27,
    "active": true,
    "date": "2025-01-23T17:21:20.929Z",
    "totalPrice": 3000
  },
  {
    "id": 28,
    "active": true,
    "date": "2025-01-23T17:47:50.392Z",
    "totalPrice": 2200
  },
  {
    "id": 29,
    "active": true,
    "date": "2025-01-23T17:55:11.067Z",
    "totalPrice": 2000
  },
  {
    "id": 30,
    "active": true,
    "date": "2025-01-23T18:09:11.590Z",
    "totalPrice": 2500
  },
  {
    "id": 31,
    "active": true,
    "date": "2025-01-23T18:52:11.041Z",
    "totalPrice": 20000
  },
  {
    "id": 32,
    "active": true,
    "date": "2025-01-23T19:38:49.325Z",
    "totalPrice": 3400
  },
  {
    "id": 33,
    "active": true,
    "date": "2025-01-23T20:34:31.356Z",
    "totalPrice": 3200
  },
  {
    "id": 34,
    "active": true,
    "date": "2025-01-23T21:00:40.378Z",
    "totalPrice": 3000
  },
  {
    "id": 35,
    "active": true,
    "date": "2025-01-23T21:36:52.939Z",
    "totalPrice": 6400
  },
  {
    "id": 36,
    "active": true,
    "date": "2025-01-23T21:41:25.388Z",
    "totalPrice": 2000
  },
  {
    "id": 37,
    "active": true,
    "date": "2025-01-23T21:49:51.902Z",
    "totalPrice": 1000
  },
  {
    "id": 38,
    "active": true,
    "date": "2025-01-24T10:20:04.689Z",
    "totalPrice": 2000
  },
  {
    "id": 39,
    "active": true,
    "date": "2025-01-24T11:35:52.211Z",
    "totalPrice": 1200
  },
  {
    "id": 40,
    "active": true,
    "date": "2025-01-24T11:51:42.239Z",
    "totalPrice": 7000
  },
  {
    "id": 41,
    "active": true,
    "date": "2025-01-24T11:55:51.065Z",
    "totalPrice": 1800
  },
  {
    "id": 42,
    "active": true,
    "date": "2025-01-24T12:21:44.063Z",
    "totalPrice": 3000
  },
  {
    "id": 43,
    "active": true,
    "date": "2025-01-24T12:35:54.819Z",
    "totalPrice": 2400
  },
  {
    "id": 44,
    "active": true,
    "date": "2025-01-24T13:16:19.333Z",
    "totalPrice": 1600
  },
  {
    "id": 45,
    "active": true,
    "date": "2025-01-24T13:19:17.518Z",
    "totalPrice": 1600
  },
  {
    "id": 46,
    "active": true,
    "date": "2025-01-24T13:41:15.148Z",
    "totalPrice": 1000
  },
  {
    "id": 47,
    "active": true,
    "date": "2025-01-24T13:53:25.439Z",
    "totalPrice": 1900
  },
  {
    "id": 48,
    "active": true,
    "date": "2025-01-24T17:09:16.989Z",
    "totalPrice": 5000
  },
  {
    "id": 49,
    "active": true,
    "date": "2025-01-24T17:11:16.558Z",
    "totalPrice": 2900
  },
  {
    "id": 50,
    "active": true,
    "date": "2025-01-24T17:16:28.008Z",
    "totalPrice": 8700
  },
  {
    "id": 51,
    "active": true,
    "date": "2025-01-24T17:34:39.181Z",
    "totalPrice": 2000
  },
  {
    "id": 52,
    "active": true,
    "date": "2025-01-24T17:44:24.751Z",
    "totalPrice": 6600
  },
  {
    "id": 53,
    "active": true,
    "date": "2025-01-24T18:22:17.162Z",
    "totalPrice": 1900
  },
  {
    "id": 54,
    "active": true,
    "date": "2025-01-24T18:38:43.189Z",
    "totalPrice": 4900
  },
  {
    "id": 55,
    "active": true,
    "date": "2025-01-24T18:40:12.542Z",
    "totalPrice": 2000
  },
  {
    "id": 56,
    "active": true,
    "date": "2025-01-24T18:45:42.488Z",
    "totalPrice": 4400
  },
  {
    "id": 57,
    "active": true,
    "date": "2025-01-24T18:56:56.139Z",
    "totalPrice": 10400
  },
  {
    "id": 58,
    "active": true,
    "date": "2025-01-24T19:22:31.770Z",
    "totalPrice": 4500
  },
  {
    "id": 59,
    "active": true,
    "date": "2025-01-24T20:14:18.414Z",
    "totalPrice": 13800
  },
  {
    "id": 60,
    "active": true,
    "date": "2025-01-24T20:19:46.479Z",
    "totalPrice": 2400
  },
  {
    "id": 61,
    "active": true,
    "date": "2025-01-24T20:38:35.652Z",
    "totalPrice": 8300
  },
  {
    "id": 62,
    "active": true,
    "date": "2025-01-24T20:42:44.413Z",
    "totalPrice": 900
  },
  {
    "id": 63,
    "active": true,
    "date": "2025-01-24T20:53:35.984Z",
    "totalPrice": 2200
  },
  {
    "id": 64,
    "active": true,
    "date": "2025-01-24T20:58:00.234Z",
    "totalPrice": 5400
  },
  {
    "id": 65,
    "active": true,
    "date": "2025-01-24T21:44:29.253Z",
    "totalPrice": 2850
  },
  {
    "id": 66,
    "active": true,
    "date": "2025-01-25T10:00:03.951Z",
    "totalPrice": 3000
  },
  {
    "id": 67,
    "active": true,
    "date": "2025-01-25T10:12:50.949Z",
    "totalPrice": 500
  },
  {
    "id": 68,
    "active": true,
    "date": "2025-01-25T10:48:41.622Z",
    "totalPrice": 8300
  },
  {
    "id": 69,
    "active": true,
    "date": "2025-01-25T10:54:49.127Z",
    "totalPrice": 3900
  },
  {
    "id": 70,
    "active": true,
    "date": "2025-01-25T12:01:22.560Z",
    "totalPrice": 2000
  },
  {
    "id": 71,
    "active": true,
    "date": "2025-01-25T12:34:34.633Z",
    "totalPrice": 1600
  },
  {
    "id": 72,
    "active": true,
    "date": "2025-01-25T12:45:50.099Z",
    "totalPrice": 1900
  },
  {
    "id": 73,
    "active": true,
    "date": "2025-01-25T13:04:00.545Z",
    "totalPrice": 6400
  },
  {
    "id": 74,
    "active": true,
    "date": "2025-01-25T13:08:44.833Z",
    "totalPrice": 2500
  },
  {
    "id": 75,
    "active": true,
    "date": "2025-01-25T13:09:03.633Z",
    "totalPrice": 800
  },
  {
    "id": 76,
    "active": true,
    "date": "2025-01-25T13:09:51.482Z",
    "totalPrice": 10300
  },
  {
    "id": 77,
    "active": true,
    "date": "2025-01-25T13:32:30.360Z",
    "totalPrice": 16440
  },
  {
    "id": 78,
    "active": true,
    "date": "2025-01-25T13:37:40.400Z",
    "totalPrice": 2000
  },
  {
    "id": 79,
    "active": true,
    "date": "2025-01-25T17:24:25.029Z",
    "totalPrice": 2100
  },
  {
    "id": 80,
    "active": true,
    "date": "2025-01-25T17:30:19.822Z",
    "totalPrice": 7200
  },
  {
    "id": 81,
    "active": true,
    "date": "2025-01-25T17:43:01.562Z",
    "totalPrice": 4000
  },
  {
    "id": 82,
    "active": true,
    "date": "2025-01-25T17:52:25.380Z",
    "totalPrice": 4500
  },
  {
    "id": 83,
    "active": true,
    "date": "2025-01-25T18:06:36.511Z",
    "totalPrice": 4800
  },
  {
    "id": 84,
    "active": true,
    "date": "2025-01-25T18:10:25.152Z",
    "totalPrice": 1500
  },
  {
    "id": 85,
    "active": true,
    "date": "2025-01-25T18:11:26.825Z",
    "totalPrice": 2300
  },
  {
    "id": 86,
    "active": true,
    "date": "2025-01-25T18:56:01.749Z",
    "totalPrice": 1500
  },
  {
    "id": 87,
    "active": true,
    "date": "2025-01-25T19:11:40.176Z",
    "totalPrice": 6500
  },
  {
    "id": 88,
    "active": true,
    "date": "2025-01-25T19:33:49.454Z",
    "totalPrice": 400
  },
  {
    "id": 89,
    "active": true,
    "date": "2025-01-25T19:37:04.447Z",
    "totalPrice": 3800
  },
  {
    "id": 90,
    "active": true,
    "date": "2025-01-25T19:37:55.663Z",
    "totalPrice": 3300
  },
  {
    "id": 91,
    "active": true,
    "date": "2025-01-25T19:39:12.327Z",
    "totalPrice": 4300
  },
  {
    "id": 92,
    "active": true,
    "date": "2025-01-25T20:04:30.086Z",
    "totalPrice": 4900
  },
  {
    "id": 93,
    "active": true,
    "date": "2025-01-25T20:07:37.286Z",
    "totalPrice": 3400
  },
  {
    "id": 94,
    "active": true,
    "date": "2025-01-25T20:09:14.384Z",
    "totalPrice": 4500
  },
  {
    "id": 95,
    "active": true,
    "date": "2025-01-25T20:13:23.130Z",
    "totalPrice": 3100
  },
  {
    "id": 96,
    "active": true,
    "date": "2025-01-25T20:21:26.674Z",
    "totalPrice": 8090
  },
  {
    "id": 97,
    "active": true,
    "date": "2025-01-25T20:22:30.234Z",
    "totalPrice": 4200
  },
  {
    "id": 98,
    "active": true,
    "date": "2025-01-25T20:27:32.868Z",
    "totalPrice": 550
  },
  {
    "id": 99,
    "active": true,
    "date": "2025-01-25T20:29:00.708Z",
    "totalPrice": 1200
  },
  {
    "id": 100,
    "active": true,
    "date": "2025-01-25T20:30:17.100Z",
    "totalPrice": 2900
  },
  {
    "id": 101,
    "active": true,
    "date": "2025-01-25T20:35:18.238Z",
    "totalPrice": 2800
  },
  {
    "id": 102,
    "active": true,
    "date": "2025-01-25T20:49:13.673Z",
    "totalPrice": 14700
  },
  {
    "id": 103,
    "active": true,
    "date": "2025-01-25T20:50:21.905Z",
    "totalPrice": 2000
  },
  {
    "id": 104,
    "active": true,
    "date": "2025-01-25T20:53:00.914Z",
    "totalPrice": 1900
  },
  {
    "id": 105,
    "active": true,
    "date": "2025-01-25T20:57:31.803Z",
    "totalPrice": 10610
  },
  {
    "id": 106,
    "active": true,
    "date": "2025-01-25T20:58:39.548Z",
    "totalPrice": 4000
  },
  {
    "id": 107,
    "active": true,
    "date": "2025-01-25T21:22:23.650Z",
    "totalPrice": 14240
  },
  {
    "id": 108,
    "active": true,
    "date": "2025-01-25T21:26:47.651Z",
    "totalPrice": 8000
  },
  {
    "id": 109,
    "active": true,
    "date": "2025-01-25T21:29:51.500Z",
    "totalPrice": 24200
  },
  {
    "id": 110,
    "active": true,
    "date": "2025-01-25T21:32:02.644Z",
    "totalPrice": 12400
  },
  {
    "id": 111,
    "active": true,
    "date": "2025-01-25T21:37:47.885Z",
    "totalPrice": 8600
  },
  {
    "id": 112,
    "active": true,
    "date": "2025-01-25T21:38:15.693Z",
    "totalPrice": 2400
  },
  {
    "id": 113,
    "active": true,
    "date": "2025-01-25T21:38:30.285Z",
    "totalPrice": 400
  },
  {
    "id": 114,
    "active": true,
    "date": "2025-01-25T21:41:52.143Z",
    "totalPrice": 9950
  },
  {
    "id": 115,
    "active": true,
    "date": "2025-01-25T21:46:29.399Z",
    "totalPrice": 7700
  },
  {
    "id": 116,
    "active": true,
    "date": "2025-01-25T21:54:27.818Z",
    "totalPrice": 5800
  },
  {
    "id": 117,
    "active": true,
    "date": "2025-01-27T09:21:25.736Z",
    "totalPrice": 1700
  },
  {
    "id": 118,
    "active": true,
    "date": "2025-01-27T09:40:24.532Z",
    "totalPrice": 1400
  },
  {
    "id": 119,
    "active": true,
    "date": "2025-01-27T09:41:30.076Z",
    "totalPrice": 880
  },
  {
    "id": 120,
    "active": true,
    "date": "2025-01-27T10:07:26.112Z",
    "totalPrice": 2000
  },
  {
    "id": 121,
    "active": true,
    "date": "2025-01-27T10:16:25.600Z",
    "totalPrice": 2800
  },
  {
    "id": 122,
    "active": true,
    "date": "2025-01-27T10:16:34.249Z",
    "totalPrice": 500
  },
  {
    "id": 123,
    "active": true,
    "date": "2025-01-27T10:24:40.859Z",
    "totalPrice": 1800
  },
  {
    "id": 124,
    "active": true,
    "date": "2025-01-27T10:40:14.542Z",
    "totalPrice": 1600
  },
  {
    "id": 126,
    "active": true,
    "date": "2025-01-27T11:50:58.572Z",
    "totalPrice": 750
  },
  {
    "id": 127,
    "active": true,
    "date": "2025-01-27T11:54:23.405Z",
    "totalPrice": 2200
  },
  {
    "id": 128,
    "active": true,
    "date": "2025-01-27T11:55:12.684Z",
    "totalPrice": 2600
  },
  {
    "id": 129,
    "active": true,
    "date": "2025-01-27T12:03:48.087Z",
    "totalPrice": 4500
  },
  {
    "id": 130,
    "active": true,
    "date": "2025-01-27T12:27:40.244Z",
    "totalPrice": 1800
  },
  {
    "id": 131,
    "active": true,
    "date": "2025-01-27T12:55:59.305Z",
    "totalPrice": 4350
  },
  {
    "id": 132,
    "active": true,
    "date": "2025-01-27T12:57:03.658Z",
    "totalPrice": 2500
  },
  {
    "id": 133,
    "active": true,
    "date": "2025-01-27T13:04:52.803Z",
    "totalPrice": 4700
  },
  {
    "id": 134,
    "active": true,
    "date": "2025-01-27T13:06:50.227Z",
    "totalPrice": 2000
  },
  {
    "id": 135,
    "active": true,
    "date": "2025-01-27T13:26:54.343Z",
    "totalPrice": 3500
  },
  {
    "id": 136,
    "active": true,
    "date": "2025-01-27T13:54:28.309Z",
    "totalPrice": 5600
  },
  {
    "id": 137,
    "active": true,
    "date": "2025-01-27T17:16:34.053Z",
    "totalPrice": 5800
  },
  {
    "id": 138,
    "active": true,
    "date": "2025-01-27T17:18:42.022Z",
    "totalPrice": 4500
  },
  {
    "id": 139,
    "active": true,
    "date": "2025-01-27T17:35:41.257Z",
    "totalPrice": 6400
  },
  {
    "id": 140,
    "active": true,
    "date": "2025-01-27T17:40:54.762Z",
    "totalPrice": 2000
  },
  {
    "id": 141,
    "active": true,
    "date": "2025-01-27T17:46:37.499Z",
    "totalPrice": 8800
  },
  {
    "id": 142,
    "active": true,
    "date": "2025-01-27T17:52:55.292Z",
    "totalPrice": 4500
  },
  {
    "id": 143,
    "active": true,
    "date": "2025-01-27T17:53:52.868Z",
    "totalPrice": 3100
  },
  {
    "id": 144,
    "active": true,
    "date": "2025-01-27T18:09:02.743Z",
    "totalPrice": 12940
  },
  {
    "id": 145,
    "active": true,
    "date": "2025-01-27T18:19:02.049Z",
    "totalPrice": 1200
  },
  {
    "id": 146,
    "active": true,
    "date": "2025-01-27T18:27:54.179Z",
    "totalPrice": 6100
  },
  {
    "id": 147,
    "active": true,
    "date": "2025-01-27T18:28:53.764Z",
    "totalPrice": 2080
  },
  {
    "id": 148,
    "active": true,
    "date": "2025-01-27T18:40:31.310Z",
    "totalPrice": 7700
  },
  {
    "id": 149,
    "active": true,
    "date": "2025-01-27T18:49:21.008Z",
    "totalPrice": 6900
  },
  {
    "id": 150,
    "active": true,
    "date": "2025-01-27T19:20:37.254Z",
    "totalPrice": 3900
  },
  {
    "id": 151,
    "active": true,
    "date": "2025-01-27T19:56:54.886Z",
    "totalPrice": 5840
  },
  {
    "id": 152,
    "active": true,
    "date": "2025-01-27T19:59:21.166Z",
    "totalPrice": 400
  },
  {
    "id": 153,
    "active": true,
    "date": "2025-01-27T20:18:42.346Z",
    "totalPrice": 2400
  },
  {
    "id": 154,
    "active": true,
    "date": "2025-01-27T20:39:27.470Z",
    "totalPrice": 6400
  },
  {
    "id": 155,
    "active": true,
    "date": "2025-01-27T20:40:12.934Z",
    "totalPrice": 6800
  },
  {
    "id": 156,
    "active": true,
    "date": "2025-01-27T20:42:01.935Z",
    "totalPrice": 1200
  },
  {
    "id": 157,
    "active": true,
    "date": "2025-01-27T20:47:56.432Z",
    "totalPrice": 5800
  },
  {
    "id": 158,
    "active": true,
    "date": "2025-01-27T20:57:43.754Z",
    "totalPrice": 2900
  },
  {
    "id": 160,
    "active": true,
    "date": "2025-01-27T21:09:58.012Z",
    "totalPrice": 3500
  },
  {
    "id": 161,
    "active": true,
    "date": "2025-01-27T21:24:56.088Z",
    "totalPrice": 3300
  },
  {
    "id": 162,
    "active": true,
    "date": "2025-01-27T21:36:18.466Z",
    "totalPrice": 12810
  },
  {
    "id": 163,
    "active": true,
    "date": "2025-01-27T21:40:29.298Z",
    "totalPrice": 5250
  },
  {
    "id": 164,
    "active": true,
    "date": "2025-01-27T21:40:58.723Z",
    "totalPrice": 4400
  },
  {
    "id": 165,
    "active": true,
    "date": "2025-01-27T21:46:00.052Z",
    "totalPrice": 6870
  },
  {
    "id": 166,
    "active": true,
    "date": "2025-01-27T21:47:33.284Z",
    "totalPrice": 6850
  },
  {
    "id": 167,
    "active": true,
    "date": "2025-01-27T21:48:47.108Z",
    "totalPrice": 1500
  },
  {
    "id": 168,
    "active": true,
    "date": "2025-01-27T21:49:08.732Z",
    "totalPrice": 3300
  },
  {
    "id": 169,
    "active": true,
    "date": "2025-01-27T21:52:19.116Z",
    "totalPrice": 4100
  },
  {
    "id": 171,
    "active": true,
    "date": "2025-01-28T09:31:39.206Z",
    "totalPrice": 1400
  },
  {
    "id": 172,
    "active": true,
    "date": "2025-01-28T09:37:08.255Z",
    "totalPrice": 1000
  },
  {
    "id": 173,
    "active": true,
    "date": "2025-01-28T09:45:31.266Z",
    "totalPrice": 2000
  },
  {
    "id": 174,
    "active": true,
    "date": "2025-01-28T10:21:11.329Z",
    "totalPrice": 1800
  },
  {
    "id": 175,
    "active": true,
    "date": "2025-01-28T10:47:32.150Z",
    "totalPrice": 5000
  },
  {
    "id": 176,
    "active": true,
    "date": "2025-01-28T11:06:59.994Z",
    "totalPrice": 2880
  },
  {
    "id": 177,
    "active": true,
    "date": "2025-01-28T11:08:56.194Z",
    "totalPrice": 1440
  },
  {
    "id": 178,
    "active": true,
    "date": "2025-01-28T11:09:27.187Z",
    "totalPrice": 2000
  },
  {
    "id": 179,
    "active": true,
    "date": "2025-01-28T12:02:24.093Z",
    "totalPrice": 2500
  },
  {
    "id": 180,
    "active": true,
    "date": "2025-01-28T12:19:10.936Z",
    "totalPrice": 4700
  },
  {
    "id": 181,
    "active": true,
    "date": "2025-01-28T12:37:15.076Z",
    "totalPrice": 6300
  },
  {
    "id": 182,
    "active": true,
    "date": "2025-01-28T12:41:16.492Z",
    "totalPrice": 2000
  },
  {
    "id": 183,
    "active": true,
    "date": "2025-01-28T12:41:53.141Z",
    "totalPrice": 2100
  },
  {
    "id": 184,
    "active": true,
    "date": "2025-01-28T12:46:53.405Z",
    "totalPrice": 5645
  },
  {
    "id": 185,
    "active": true,
    "date": "2025-01-28T12:55:24.551Z",
    "totalPrice": 9000
  },
  {
    "id": 186,
    "active": true,
    "date": "2025-01-28T12:56:02.335Z",
    "totalPrice": 1440
  },
  {
    "id": 187,
    "active": true,
    "date": "2025-01-28T12:57:32.905Z",
    "totalPrice": 1200
  },
  {
    "id": 188,
    "active": true,
    "date": "2025-01-28T13:00:38.833Z",
    "totalPrice": 3720
  },
  {
    "id": 189,
    "active": true,
    "date": "2025-01-28T13:29:54.950Z",
    "totalPrice": 2800
  },
  {
    "id": 190,
    "active": true,
    "date": "2025-01-28T13:33:49.136Z",
    "totalPrice": 7000
  },
  {
    "id": 191,
    "active": true,
    "date": "2025-01-28T13:38:59.217Z",
    "totalPrice": 7825
  },
  {
    "id": 192,
    "active": true,
    "date": "2025-01-28T13:43:00.497Z",
    "totalPrice": 2700
  },
  {
    "id": 193,
    "active": true,
    "date": "2025-01-28T17:10:46.644Z",
    "totalPrice": 5600
  },
  {
    "id": 194,
    "active": true,
    "date": "2025-01-28T17:16:27.260Z",
    "totalPrice": 3500
  },
  {
    "id": 195,
    "active": true,
    "date": "2025-01-28T17:19:25.293Z",
    "totalPrice": 1500
  },
  {
    "id": 196,
    "active": true,
    "date": "2025-01-28T17:20:37.173Z",
    "totalPrice": 2700
  },
  {
    "id": 197,
    "active": true,
    "date": "2025-01-28T17:21:42.365Z",
    "totalPrice": 2300
  },
  {
    "id": 198,
    "active": true,
    "date": "2025-01-28T17:32:18.911Z",
    "totalPrice": 4800
  },
  {
    "id": 199,
    "active": true,
    "date": "2025-01-28T17:34:31.208Z",
    "totalPrice": 5400
  },
  {
    "id": 200,
    "active": true,
    "date": "2025-01-28T17:35:01.272Z",
    "totalPrice": 100
  },
  {
    "id": 201,
    "active": true,
    "date": "2025-01-28T17:43:22.617Z",
    "totalPrice": 1600
  },
  {
    "id": 202,
    "active": true,
    "date": "2025-01-28T17:49:35.370Z",
    "totalPrice": 2500
  },
  {
    "id": 203,
    "active": true,
    "date": "2025-01-28T17:49:54.634Z",
    "totalPrice": 2000
  },
  {
    "id": 204,
    "active": true,
    "date": "2025-01-28T18:20:39.681Z",
    "totalPrice": 11300
  },
  {
    "id": 205,
    "active": true,
    "date": "2025-01-28T18:22:52.002Z",
    "totalPrice": 1500
  },
  {
    "id": 206,
    "active": true,
    "date": "2025-01-28T18:44:26.086Z",
    "totalPrice": 9090
  },
  {
    "id": 207,
    "active": true,
    "date": "2025-01-28T18:48:04.038Z",
    "totalPrice": 8235
  },
  {
    "id": 208,
    "active": true,
    "date": "2025-01-28T18:56:01.032Z",
    "totalPrice": 12600
  },
  {
    "id": 209,
    "active": true,
    "date": "2025-01-28T19:05:29.755Z",
    "totalPrice": 5800
  },
  {
    "id": 210,
    "active": true,
    "date": "2025-01-28T19:06:18.162Z",
    "totalPrice": 7140
  },
  {
    "id": 211,
    "active": true,
    "date": "2025-01-28T19:07:26.979Z",
    "totalPrice": 2500
  },
  {
    "id": 212,
    "active": true,
    "date": "2025-01-28T19:14:00.740Z",
    "totalPrice": 13625
  },
  {
    "id": 213,
    "active": true,
    "date": "2025-01-28T19:15:48.005Z",
    "totalPrice": 5000
  },
  {
    "id": 214,
    "active": true,
    "date": "2025-01-28T19:23:30.429Z",
    "totalPrice": 3100
  },
  {
    "id": 215,
    "active": true,
    "date": "2025-01-28T19:27:40.758Z",
    "totalPrice": 3900
  },
  {
    "id": 216,
    "active": true,
    "date": "2025-01-28T19:38:07.337Z",
    "totalPrice": 7780
  },
  {
    "id": 217,
    "active": true,
    "date": "2025-01-28T19:40:49.665Z",
    "totalPrice": 800
  },
  {
    "id": 218,
    "active": true,
    "date": "2025-01-28T19:52:59.172Z",
    "totalPrice": 10400
  },
  {
    "id": 219,
    "active": true,
    "date": "2025-01-28T19:55:57.412Z",
    "totalPrice": 4530
  },
  {
    "id": 220,
    "active": true,
    "date": "2025-01-28T20:00:02.222Z",
    "totalPrice": 10300
  },
  {
    "id": 221,
    "active": true,
    "date": "2025-01-28T20:02:26.845Z",
    "totalPrice": 3200
  },
  {
    "id": 222,
    "active": true,
    "date": "2025-01-28T20:17:17.361Z",
    "totalPrice": 8200
  },
  {
    "id": 223,
    "active": true,
    "date": "2025-01-28T20:18:02.569Z",
    "totalPrice": 9200
  },
  {
    "id": 224,
    "active": true,
    "date": "2025-01-28T20:19:57.026Z",
    "totalPrice": 3200
  },
  {
    "id": 225,
    "active": true,
    "date": "2025-01-28T20:41:42.965Z",
    "totalPrice": 30380
  },
  {
    "id": 226,
    "active": true,
    "date": "2025-01-28T20:45:51.847Z",
    "totalPrice": 500
  },
  {
    "id": 227,
    "active": true,
    "date": "2025-01-28T20:58:25.921Z",
    "totalPrice": 13960
  },
  {
    "id": 228,
    "active": true,
    "date": "2025-01-28T21:05:02.402Z",
    "totalPrice": 11400
  },
  {
    "id": 229,
    "active": true,
    "date": "2025-01-28T21:06:50.810Z",
    "totalPrice": 6600
  },
  {
    "id": 230,
    "active": true,
    "date": "2025-01-28T21:08:16.915Z",
    "totalPrice": 1500
  },
  {
    "id": 231,
    "active": true,
    "date": "2025-01-28T21:17:04.285Z",
    "totalPrice": 2500
  },
  {
    "id": 232,
    "active": true,
    "date": "2025-01-28T21:29:21.559Z",
    "totalPrice": 3100
  },
  {
    "id": 233,
    "active": true,
    "date": "2025-01-28T21:31:51.175Z",
    "totalPrice": 4500
  },
  {
    "id": 234,
    "active": true,
    "date": "2025-01-28T21:42:50.834Z",
    "totalPrice": 10700
  },
  {
    "id": 235,
    "active": true,
    "date": "2025-01-28T21:47:15.779Z",
    "totalPrice": 21800
  },
  {
    "id": 236,
    "active": true,
    "date": "2025-01-28T21:48:18.579Z",
    "totalPrice": 6900
  },
  {
    "id": 237,
    "active": true,
    "date": "2025-01-28T21:49:33.563Z",
    "totalPrice": 1500
  },
  {
    "id": 238,
    "active": true,
    "date": "2025-01-28T21:51:45.596Z",
    "totalPrice": 2145
  },
  {
    "id": 239,
    "active": true,
    "date": "2025-01-28T21:56:01.781Z",
    "totalPrice": 2000
  },
  {
    "id": 240,
    "active": true,
    "date": "2025-01-28T21:58:45.117Z",
    "totalPrice": 8300
  },
  {
    "id": 241,
    "active": true,
    "date": "2025-01-29T10:32:53.704Z",
    "totalPrice": 2600
  },
  {
    "id": 242,
    "active": true,
    "date": "2025-01-29T10:56:12.230Z",
    "totalPrice": 1900
  },
  {
    "id": 243,
    "active": true,
    "date": "2025-01-29T11:25:55.771Z",
    "totalPrice": 1200
  },
  {
    "id": 244,
    "active": true,
    "date": "2025-01-29T12:14:22.926Z",
    "totalPrice": 13320
  },
  {
    "id": 245,
    "active": true,
    "date": "2025-01-29T12:15:43.996Z",
    "totalPrice": 6000
  },
  {
    "id": 246,
    "active": true,
    "date": "2025-01-29T12:16:51.541Z",
    "totalPrice": 4500
  },
  {
    "id": 247,
    "active": true,
    "date": "2025-01-29T12:19:38.533Z",
    "totalPrice": 9000
  },
  {
    "id": 248,
    "active": true,
    "date": "2025-01-29T12:24:16.919Z",
    "totalPrice": 3900
  },
  {
    "id": 249,
    "active": true,
    "date": "2025-01-29T12:47:32.035Z",
    "totalPrice": 3100
  },
  {
    "id": 250,
    "active": true,
    "date": "2025-01-29T12:54:26.781Z",
    "totalPrice": 13300
  },
  {
    "id": 251,
    "active": true,
    "date": "2025-01-29T13:03:20.846Z",
    "totalPrice": 1200
  },
  {
    "id": 252,
    "active": true,
    "date": "2025-01-29T13:34:52.854Z",
    "totalPrice": 2200
  },
  {
    "id": 253,
    "active": true,
    "date": "2025-01-29T13:47:33.752Z",
    "totalPrice": 3600
  },
  {
    "id": 254,
    "active": true,
    "date": "2025-01-29T17:10:57.072Z",
    "totalPrice": 2200
  },
  {
    "id": 255,
    "active": true,
    "date": "2025-01-29T17:11:07.552Z",
    "totalPrice": 2500
  },
  {
    "id": 256,
    "active": true,
    "date": "2025-01-29T17:18:35.555Z",
    "totalPrice": 2000
  },
  {
    "id": 257,
    "active": true,
    "date": "2025-01-29T17:44:17.001Z",
    "totalPrice": 3000
  },
  {
    "id": 258,
    "active": true,
    "date": "2025-01-29T17:44:54.071Z",
    "totalPrice": 2800
  },
  {
    "id": 259,
    "active": true,
    "date": "2025-01-29T18:13:29.413Z",
    "totalPrice": 2000
  },
  {
    "id": 260,
    "active": true,
    "date": "2025-01-29T18:35:24.394Z",
    "totalPrice": 11700
  },
  {
    "id": 261,
    "active": true,
    "date": "2025-01-29T18:36:07.282Z",
    "totalPrice": 4300
  },
  {
    "id": 262,
    "active": true,
    "date": "2025-01-29T18:39:37.394Z",
    "totalPrice": 1400
  },
  {
    "id": 263,
    "active": true,
    "date": "2025-01-29T19:04:36.384Z",
    "totalPrice": 2200
  },
  {
    "id": 264,
    "active": true,
    "date": "2025-01-29T19:16:07.225Z",
    "totalPrice": 4800
  },
  {
    "id": 265,
    "active": true,
    "date": "2025-01-29T19:19:45.451Z",
    "totalPrice": 2700
  },
  {
    "id": 266,
    "active": true,
    "date": "2025-01-29T19:21:28.563Z",
    "totalPrice": 9500
  },
  {
    "id": 267,
    "active": true,
    "date": "2025-01-29T19:59:56.404Z",
    "totalPrice": 6800
  },
  {
    "id": 268,
    "active": true,
    "date": "2025-01-29T20:01:11.387Z",
    "totalPrice": 1500
  },
  {
    "id": 269,
    "active": true,
    "date": "2025-01-29T20:23:05.911Z",
    "totalPrice": 21700
  },
  {
    "id": 270,
    "active": true,
    "date": "2025-01-29T20:25:28.471Z",
    "totalPrice": 5900
  },
  {
    "id": 271,
    "active": true,
    "date": "2025-01-29T20:31:14.033Z",
    "totalPrice": 11310
  },
  {
    "id": 272,
    "active": true,
    "date": "2025-01-29T20:36:06.954Z",
    "totalPrice": 11200
  },
  {
    "id": 273,
    "active": true,
    "date": "2025-01-29T20:37:24.666Z",
    "totalPrice": 1800
  },
  {
    "id": 274,
    "active": true,
    "date": "2025-01-29T20:39:46.171Z",
    "totalPrice": 3000
  },
  {
    "id": 275,
    "active": true,
    "date": "2025-01-29T20:41:40.387Z",
    "totalPrice": 4500
  },
  {
    "id": 276,
    "active": true,
    "date": "2025-01-29T20:53:31.486Z",
    "totalPrice": 11300
  },
  {
    "id": 277,
    "active": true,
    "date": "2025-01-29T20:58:59.070Z",
    "totalPrice": 16700
  },
  {
    "id": 278,
    "active": true,
    "date": "2025-01-29T21:02:47.871Z",
    "totalPrice": 3600
  },
  {
    "id": 279,
    "active": true,
    "date": "2025-01-29T21:03:04.800Z",
    "totalPrice": 2200
  },
  {
    "id": 280,
    "active": true,
    "date": "2025-01-29T21:12:03.929Z",
    "totalPrice": 19700
  },
  {
    "id": 281,
    "active": true,
    "date": "2025-01-29T21:15:13.946Z",
    "totalPrice": 11100
  },
  {
    "id": 282,
    "active": true,
    "date": "2025-01-29T21:20:13.170Z",
    "totalPrice": 6300
  },
  {
    "id": 283,
    "active": true,
    "date": "2025-01-29T21:21:36.298Z",
    "totalPrice": 9800
  },
  {
    "id": 284,
    "active": true,
    "date": "2025-01-29T21:31:38.405Z",
    "totalPrice": 4200
  },
  {
    "id": 285,
    "active": true,
    "date": "2025-01-29T21:41:30.351Z",
    "totalPrice": 1300
  },
  {
    "id": 286,
    "active": true,
    "date": "2025-01-29T21:42:06.551Z",
    "totalPrice": 400
  },
  {
    "id": 287,
    "active": true,
    "date": "2025-01-29T21:47:47.400Z",
    "totalPrice": 8700
  },
  {
    "id": 288,
    "active": true,
    "date": "2025-01-30T09:39:28.823Z",
    "totalPrice": 6500
  },
  {
    "id": 289,
    "active": true,
    "date": "2025-01-30T09:54:04.991Z",
    "totalPrice": 3400
  },
  {
    "id": 290,
    "active": true,
    "date": "2025-01-30T10:26:12.182Z",
    "totalPrice": 1000
  },
  {
    "id": 291,
    "active": true,
    "date": "2025-01-30T10:59:28.661Z",
    "totalPrice": 4000
  },
  {
    "id": 292,
    "active": true,
    "date": "2025-01-30T11:02:47.621Z",
    "totalPrice": 2700
  },
  {
    "id": 293,
    "active": true,
    "date": "2025-01-30T11:09:44.390Z",
    "totalPrice": 3000
  },
  {
    "id": 294,
    "active": true,
    "date": "2025-01-30T11:13:44.215Z",
    "totalPrice": 16080
  },
  {
    "id": 295,
    "active": true,
    "date": "2025-01-30T11:18:29.224Z",
    "totalPrice": 700
  },
  {
    "id": 296,
    "active": true,
    "date": "2025-01-30T11:49:33.806Z",
    "totalPrice": 350
  },
  {
    "id": 297,
    "active": true,
    "date": "2025-01-30T11:58:35.616Z",
    "totalPrice": 1500
  },
  {
    "id": 298,
    "active": true,
    "date": "2025-01-30T12:18:53.741Z",
    "totalPrice": 8100
  },
  {
    "id": 299,
    "active": true,
    "date": "2025-01-30T12:19:33.021Z",
    "totalPrice": 2300
  },
  {
    "id": 300,
    "active": true,
    "date": "2025-01-30T12:31:21.687Z",
    "totalPrice": 3600
  },
  {
    "id": 301,
    "active": true,
    "date": "2025-01-30T12:35:58.031Z",
    "totalPrice": 2500
  },
  {
    "id": 302,
    "active": true,
    "date": "2025-01-30T12:39:48.824Z",
    "totalPrice": 2000
  },
  {
    "id": 303,
    "active": true,
    "date": "2025-01-30T12:46:51.538Z",
    "totalPrice": 6300
  },
  {
    "id": 304,
    "active": true,
    "date": "2025-01-30T12:55:30.028Z",
    "totalPrice": 3800
  },
  {
    "id": 306,
    "active": true,
    "date": "2025-01-30T13:10:05.823Z",
    "totalPrice": 2400
  },
  {
    "id": 307,
    "active": true,
    "date": "2025-01-30T13:14:00.607Z",
    "totalPrice": 6800
  },
  {
    "id": 308,
    "active": true,
    "date": "2025-01-30T13:20:40.600Z",
    "totalPrice": 1500
  },
  {
    "id": 309,
    "active": true,
    "date": "2025-01-30T13:23:22.842Z",
    "totalPrice": 2500
  },
  {
    "id": 310,
    "active": true,
    "date": "2025-01-30T13:29:14.930Z",
    "totalPrice": 1400
  },
  {
    "id": 312,
    "active": true,
    "date": "2025-01-30T17:14:02.228Z",
    "totalPrice": 2000
  },
  {
    "id": 313,
    "active": true,
    "date": "2025-01-30T17:15:35.876Z",
    "totalPrice": 3000
  },
  {
    "id": 314,
    "active": true,
    "date": "2025-01-30T17:16:24.172Z",
    "totalPrice": 2200
  },
  {
    "id": 315,
    "active": true,
    "date": "2025-01-30T17:20:19.549Z",
    "totalPrice": 3000
  },
  {
    "id": 316,
    "active": true,
    "date": "2025-01-30T17:28:40.327Z",
    "totalPrice": 2800
  },
  {
    "id": 317,
    "active": true,
    "date": "2025-01-30T17:35:05.945Z",
    "totalPrice": 5700
  },
  {
    "id": 318,
    "active": true,
    "date": "2025-01-30T17:39:19.769Z",
    "totalPrice": 2000
  },
  {
    "id": 319,
    "active": true,
    "date": "2025-01-30T18:01:12.670Z",
    "totalPrice": 1500
  },
  {
    "id": 320,
    "active": true,
    "date": "2025-01-30T18:13:48.760Z",
    "totalPrice": 1500
  },
  {
    "id": 321,
    "active": true,
    "date": "2025-01-30T18:22:29.466Z",
    "totalPrice": 3800
  },
  {
    "id": 322,
    "active": true,
    "date": "2025-01-30T18:47:46.032Z",
    "totalPrice": 2500
  },
  {
    "id": 323,
    "active": true,
    "date": "2025-01-30T18:55:46.169Z",
    "totalPrice": 10000
  },
  {
    "id": 324,
    "active": true,
    "date": "2025-01-30T19:04:02.803Z",
    "totalPrice": 2000
  },
  {
    "id": 325,
    "active": true,
    "date": "2025-01-30T19:08:56.115Z",
    "totalPrice": 10590
  },
  {
    "id": 326,
    "active": true,
    "date": "2025-01-30T19:15:01.533Z",
    "totalPrice": 5000
  },
  {
    "id": 327,
    "active": true,
    "date": "2025-01-30T19:16:16.468Z",
    "totalPrice": 10800
  },
  {
    "id": 328,
    "active": true,
    "date": "2025-01-30T19:31:25.912Z",
    "totalPrice": 2600
  },
  {
    "id": 329,
    "active": true,
    "date": "2025-01-30T19:36:42.849Z",
    "totalPrice": 1900
  },
  {
    "id": 330,
    "active": true,
    "date": "2025-01-30T20:07:08.455Z",
    "totalPrice": 6100
  },
  {
    "id": 331,
    "active": true,
    "date": "2025-01-30T20:10:20.191Z",
    "totalPrice": 12400
  },
  {
    "id": 332,
    "active": true,
    "date": "2025-01-30T20:12:35.656Z",
    "totalPrice": 5200
  },
  {
    "id": 333,
    "active": true,
    "date": "2025-01-30T20:42:23.070Z",
    "totalPrice": 6400
  },
  {
    "id": 334,
    "active": true,
    "date": "2025-01-30T20:47:13.784Z",
    "totalPrice": 2500
  },
  {
    "id": 335,
    "active": true,
    "date": "2025-01-30T20:53:48.512Z",
    "totalPrice": 5100
  },
  {
    "id": 336,
    "active": true,
    "date": "2025-01-30T20:54:17.368Z",
    "totalPrice": 2500
  },
  {
    "id": 337,
    "active": true,
    "date": "2025-01-30T20:55:17.977Z",
    "totalPrice": 5000
  },
  {
    "id": 338,
    "active": true,
    "date": "2025-01-30T21:02:49.026Z",
    "totalPrice": 4300
  },
  {
    "id": 339,
    "active": true,
    "date": "2025-01-30T21:07:40.963Z",
    "totalPrice": 1900
  },
  {
    "id": 340,
    "active": true,
    "date": "2025-01-30T21:10:55.020Z",
    "totalPrice": 3600
  },
  {
    "id": 341,
    "active": true,
    "date": "2025-01-30T21:13:50.940Z",
    "totalPrice": 3100
  },
  {
    "id": 342,
    "active": true,
    "date": "2025-01-30T21:21:15.454Z",
    "totalPrice": 7975
  },
  {
    "id": 343,
    "active": true,
    "date": "2025-01-30T21:30:00.944Z",
    "totalPrice": 1000
  },
  {
    "id": 344,
    "active": true,
    "date": "2025-01-30T21:51:12.340Z",
    "totalPrice": 1900
  },
  {
    "id": 345,
    "active": true,
    "date": "2025-01-30T21:52:06.709Z",
    "totalPrice": 2300
  },
  {
    "id": 346,
    "active": true,
    "date": "2025-01-30T21:52:31.108Z",
    "totalPrice": 900
  },
  {
    "id": 347,
    "active": true,
    "date": "2025-01-30T21:54:52.948Z",
    "totalPrice": 1200
  },
  {
    "id": 348,
    "active": true,
    "date": "2025-01-31T09:31:54.467Z",
    "totalPrice": 2500
  },
  {
    "id": 349,
    "active": true,
    "date": "2025-01-31T09:46:26.094Z",
    "totalPrice": 2800
  },
  {
    "id": 350,
    "active": true,
    "date": "2025-01-31T10:39:06.545Z",
    "totalPrice": 1700
  },
  {
    "id": 351,
    "active": true,
    "date": "2025-01-31T10:41:45.538Z",
    "totalPrice": 4892
  },
  {
    "id": 352,
    "active": true,
    "date": "2025-01-31T10:45:41.826Z",
    "totalPrice": 3500
  },
  {
    "id": 353,
    "active": true,
    "date": "2025-01-31T10:51:35.579Z",
    "totalPrice": 2800
  },
  {
    "id": 354,
    "active": true,
    "date": "2025-01-31T11:00:41.917Z",
    "totalPrice": 6000
  },
  {
    "id": 355,
    "active": true,
    "date": "2025-01-31T11:15:36.592Z",
    "totalPrice": 1400
  },
  {
    "id": 356,
    "active": true,
    "date": "2025-01-31T11:37:37.156Z",
    "totalPrice": 1250
  },
  {
    "id": 357,
    "active": true,
    "date": "2025-01-31T11:38:43.061Z",
    "totalPrice": 3750
  },
  {
    "id": 358,
    "active": true,
    "date": "2025-01-31T11:39:01.325Z",
    "totalPrice": 2200
  },
  {
    "id": 359,
    "active": true,
    "date": "2025-01-31T11:46:29.950Z",
    "totalPrice": 3050
  },
  {
    "id": 360,
    "active": true,
    "date": "2025-01-31T11:50:40.415Z",
    "totalPrice": 2000
  },
  {
    "id": 361,
    "active": true,
    "date": "2025-01-31T12:11:19.315Z",
    "totalPrice": 2300
  },
  {
    "id": 362,
    "active": true,
    "date": "2025-01-31T12:14:48.021Z",
    "totalPrice": 16170
  },
  {
    "id": 363,
    "active": true,
    "date": "2025-01-31T12:15:33.109Z",
    "totalPrice": 1200
  },
  {
    "id": 364,
    "active": true,
    "date": "2025-01-31T12:17:11.124Z",
    "totalPrice": 28300
  },
  {
    "id": 365,
    "active": true,
    "date": "2025-01-31T12:18:08.077Z",
    "totalPrice": 6800
  },
  {
    "id": 366,
    "active": true,
    "date": "2025-01-31T12:18:50.613Z",
    "totalPrice": 4000
  },
  {
    "id": 367,
    "active": true,
    "date": "2025-01-31T12:26:50.231Z",
    "totalPrice": 4000
  },
  {
    "id": 368,
    "active": true,
    "date": "2025-01-31T12:34:27.464Z",
    "totalPrice": 14020
  },
  {
    "id": 369,
    "active": true,
    "date": "2025-01-31T12:55:22.805Z",
    "totalPrice": 2800
  },
  {
    "id": 370,
    "active": true,
    "date": "2025-01-31T13:09:05.376Z",
    "totalPrice": 7100
  },
  {
    "id": 372,
    "active": true,
    "date": "2025-01-31T13:12:39.824Z",
    "totalPrice": 3680
  },
  {
    "id": 373,
    "active": true,
    "date": "2025-01-31T13:14:14.985Z",
    "totalPrice": 1500
  },
  {
    "id": 374,
    "active": true,
    "date": "2025-01-31T17:09:13.771Z",
    "totalPrice": 9160
  },
  {
    "id": 375,
    "active": true,
    "date": "2025-01-31T17:15:18.171Z",
    "totalPrice": 3000
  },
  {
    "id": 376,
    "active": true,
    "date": "2025-01-31T17:30:15.134Z",
    "totalPrice": 1200
  },
  {
    "id": 377,
    "active": true,
    "date": "2025-01-31T17:31:46.295Z",
    "totalPrice": 3200
  },
  {
    "id": 378,
    "active": true,
    "date": "2025-01-31T17:33:33.199Z",
    "totalPrice": 4990
  },
  {
    "id": 379,
    "active": true,
    "date": "2025-01-31T18:06:30.277Z",
    "totalPrice": 14920
  },
  {
    "id": 380,
    "active": true,
    "date": "2025-01-31T18:17:13.617Z",
    "totalPrice": 2200
  },
  {
    "id": 381,
    "active": true,
    "date": "2025-01-31T18:26:55.874Z",
    "totalPrice": 3000
  },
  {
    "id": 382,
    "active": true,
    "date": "2025-01-31T18:32:29.435Z",
    "totalPrice": 5800
  },
  {
    "id": 383,
    "active": true,
    "date": "2025-01-31T18:43:23.678Z",
    "totalPrice": 12800
  },
  {
    "id": 384,
    "active": true,
    "date": "2025-01-31T18:44:38.901Z",
    "totalPrice": 6800
  },
  {
    "id": 385,
    "active": true,
    "date": "2025-01-31T18:47:14.358Z",
    "totalPrice": 3000
  },
  {
    "id": 386,
    "active": true,
    "date": "2025-01-31T19:24:20.557Z",
    "totalPrice": 7790
  },
  {
    "id": 387,
    "active": true,
    "date": "2025-01-31T19:28:24.727Z",
    "totalPrice": 14430
  },
  {
    "id": 388,
    "active": true,
    "date": "2025-01-31T19:34:07.943Z",
    "totalPrice": 5900
  },
  {
    "id": 389,
    "active": true,
    "date": "2025-01-31T19:37:48.337Z",
    "totalPrice": 15055
  },
  {
    "id": 390,
    "active": true,
    "date": "2025-01-31T19:39:01.032Z",
    "totalPrice": 5600
  },
  {
    "id": 391,
    "active": true,
    "date": "2025-01-31T19:46:01.970Z",
    "totalPrice": 1900
  },
  {
    "id": 392,
    "active": true,
    "date": "2025-01-31T19:49:31.476Z",
    "totalPrice": 13100
  },
  {
    "id": 393,
    "active": true,
    "date": "2025-01-31T19:50:00.700Z",
    "totalPrice": 300
  },
  {
    "id": 394,
    "active": true,
    "date": "2025-01-31T19:53:14.988Z",
    "totalPrice": 3600
  },
  {
    "id": 395,
    "active": true,
    "date": "2025-01-31T19:55:41.836Z",
    "totalPrice": 2800
  },
  {
    "id": 396,
    "active": true,
    "date": "2025-01-31T20:03:57.213Z",
    "totalPrice": 4300
  },
  {
    "id": 397,
    "active": true,
    "date": "2025-01-31T20:04:53.189Z",
    "totalPrice": 1500
  },
  {
    "id": 398,
    "active": true,
    "date": "2025-01-31T20:05:48.351Z",
    "totalPrice": 18900
  },
  {
    "id": 399,
    "active": true,
    "date": "2025-01-31T20:23:24.001Z",
    "totalPrice": 14800
  },
  {
    "id": 400,
    "active": true,
    "date": "2025-01-31T20:24:29.514Z",
    "totalPrice": 3200
  },
  {
    "id": 401,
    "active": true,
    "date": "2025-01-31T20:27:47.715Z",
    "totalPrice": 10000
  },
  {
    "id": 402,
    "active": true,
    "date": "2025-01-31T20:35:44.556Z",
    "totalPrice": 6400
  },
  {
    "id": 403,
    "active": true,
    "date": "2025-01-31T20:41:10.997Z",
    "totalPrice": 4300
  },
  {
    "id": 404,
    "active": true,
    "date": "2025-01-31T20:45:35.870Z",
    "totalPrice": 18000
  },
  {
    "id": 405,
    "active": true,
    "date": "2025-01-31T20:48:49.886Z",
    "totalPrice": 7640
  },
  {
    "id": 406,
    "active": true,
    "date": "2025-01-31T20:50:26.247Z",
    "totalPrice": 3500
  },
  {
    "id": 407,
    "active": true,
    "date": "2025-01-31T20:53:34.311Z",
    "totalPrice": 1700
  },
  {
    "id": 408,
    "active": true,
    "date": "2025-01-31T20:57:12.217Z",
    "totalPrice": 6800
  },
  {
    "id": 409,
    "active": true,
    "date": "2025-01-31T20:59:33.138Z",
    "totalPrice": 4240
  }
]